gym_starter_kit-0.0.3.dist-info/DESCRIPTION.rst
gym_starter_kit-0.0.3.dist-info/METADATA
gym_starter_kit-0.0.3.dist-info/RECORD
gym_starter_kit-0.0.3.dist-info/WHEEL
gym_starter_kit-0.0.3.dist-info/entry_points.txt
gym_starter_kit-0.0.3.dist-info/metadata.json
gym_starter_kit-0.0.3.dist-info/top_level.txt
gymkit/__init__.py
gymkit/agent/__init__.py
gymkit/agent/gym_agent.py
gymkit/agent/random_agent.py
